dtyp/__init__.py
dtyp/_modidx.py
dtyp/atyp.py
dtyp/cons.py
dtyp/dcls.py
dtyp/grds.py
dtyp/util.py
dtyp-0.0.35.dist-info/LICENSE
dtyp-0.0.35.dist-info/METADATA
dtyp-0.0.35.dist-info/WHEEL
dtyp-0.0.35.dist-info/entry_points.txt
dtyp-0.0.35.dist-info/top_level.txt
dtyp-0.0.35.dist-info/RECORD
