Metadata-Version: 2.1
Name: dtyp
Version: 0.0.35
Summary: typed dict utilities
Home-page: https://github.com/dsm-72/dtyp
Author: dsm-72
Author-email: sumner.magruder@yale.edu
License: Apache Software License 2.0
Keywords: nbdev jupyter notebook python
Classifier: Development Status :: 4 - Beta
Classifier: Intended Audience :: Developers
Classifier: Natural Language :: English
Classifier: Programming Language :: Python :: 3.11
Classifier: License :: OSI Approved :: Apache Software License
Requires-Python: >=3.11
License-File: LICENSE
Provides-Extra: dev
Requires-Dist: numpy ; extra == 'dev'
Requires-Dist: pandas ; extra == 'dev'
Requires-Dist: torch ; extra == 'dev'
Requires-Dist: torchvision ; extra == 'dev'
Requires-Dist: pytorch-lightning ; extra == 'dev'
